secretsmanager/__init__.py
secretsmanager/_version.py
secretsmanager/secretsmanager.py
tests/__init__.py
tests/conftest.py
tests/test_secretsmanager.py
secretsmanager_illumidesk-0.0.2.dist-info/LICENSE
secretsmanager_illumidesk-0.0.2.dist-info/METADATA
secretsmanager_illumidesk-0.0.2.dist-info/WHEEL
secretsmanager_illumidesk-0.0.2.dist-info/top_level.txt
secretsmanager_illumidesk-0.0.2.dist-info/RECORD
